sphinx_comments/__init__.py
sphinx_comments-0.0.3.dist-info/LICENSE
sphinx_comments-0.0.3.dist-info/METADATA
sphinx_comments-0.0.3.dist-info/WHEEL
sphinx_comments-0.0.3.dist-info/top_level.txt
sphinx_comments-0.0.3.dist-info/RECORD
