Metadata-Version: 2.1
Name: sphinx-comments
Version: 0.0.3
Summary: Add comments and annotation to your documentation.
Home-page: https://github.com/executablebooks/sphinx-comments
Author: Executable Book Project
License: MIT License
Platform: UNKNOWN
Classifier: License :: OSI Approved :: MIT License
Provides-Extra: code_style
Provides-Extra: sphinx
Provides-Extra: testing
